{
	"Gate Swap" : [],
	"Ref Des" : [],
	"Pin Swap" : [],
	"Component Property" : [],
	"Net Property" : [
		{
			"Name" : "USB_DM",
			"C_PATH" : "@\\nrd52840 circuit\\.schematic1(sch_1):usb_dm",
			"PropName" : "DIFFERENTIAL_PAIR",
			"Logical" : null,
			"Physical" : "DP-USB"
		},
		{
			"Name" : "USB_DP",
			"C_PATH" : "@\\nrd52840 circuit\\.schematic1(sch_1):usb_dp",
			"PropName" : "DIFFERENTIAL_PAIR",
			"Logical" : null,
			"Physical" : "DP-USB"
		}
	],
	"Pin Property" : [],
	"Component" : [
		{
			"Name" : "L1",
			"C_PATH" : "@\\nrd52840 circuit\\.schematic1(sch_1):ins25647@templates.\\inductor.normal\\(chips)",
			"Logical" : null,
			"Physical" : "L1"
		},
		{
			"Name" : "L2",
			"C_PATH" : "@\\nrd52840 circuit\\.schematic1(sch_1):ins17842@templates.\\inductor.normal\\(chips)",
			"Logical" : null,
			"Physical" : "L2"
		},
		{
			"Name" : "L3",
			"C_PATH" : "@\\nrd52840 circuit\\.schematic1(sch_1):ins17868@templates.\\inductor.normal\\(chips)",
			"Logical" : null,
			"Physical" : "L3"
		},
		{
			"Name" : "L1",
			"C_PATH" : "@\\nrd52840 circuit\\.schematic1(sch_1):ins41059@templates.\\inductor.normal\\(chips)",
			"Logical" : "L1",
			"Physical" : null
		},
		{
			"Name" : "L2",
			"C_PATH" : "@\\nrd52840 circuit\\.schematic1(sch_1):ins40929@templates.\\inductor.normal\\(chips)",
			"Logical" : "L2",
			"Physical" : null
		},
		{
			"Name" : "L3",
			"C_PATH" : "@\\nrd52840 circuit\\.schematic1(sch_1):ins40991@templates.\\inductor.normal\\(chips)",
			"Logical" : "L3",
			"Physical" : null
		}
	],
	"Net" : [
		{
			"Name" : "N178521",
			"C_PATH" : "@\\nrd52840 circuit\\.schematic1(sch_1):n178521",
			"Logical" : null,
			"Physical" : "N178521"
		},
		{
			"Name" : "N409391",
			"C_PATH" : "@\\nrd52840 circuit\\.schematic1(sch_1):n409391",
			"Logical" : "N409391",
			"Physical" : null
		}
	],
	"Connection" : [
		{
			"Name" : "L1.1",
			"C_PATH" : "@\\nrd52840 circuit\\.schematic1(sch_1):ins41059@templates.\\inductor.normal\\(chips):\\1\\",
			"Logical" : "N25679",
			"Physical" : null
		},
		{
			"Name" : "L1.2",
			"C_PATH" : "@\\nrd52840 circuit\\.schematic1(sch_1):ins41059@templates.\\inductor.normal\\(chips):\\2\\",
			"Logical" : "VDD_NRF",
			"Physical" : null
		},
		{
			"Name" : "L2.2",
			"C_PATH" : "@\\nrd52840 circuit\\.schematic1(sch_1):ins40929@templates.\\inductor.normal\\(chips):\\2\\",
			"Logical" : "N409391",
			"Physical" : null
		},
		{
			"Name" : "L2.1",
			"C_PATH" : "@\\nrd52840 circuit\\.schematic1(sch_1):ins40929@templates.\\inductor.normal\\(chips):\\1\\",
			"Logical" : "N18057",
			"Physical" : null
		},
		{
			"Name" : "L3.1",
			"C_PATH" : "@\\nrd52840 circuit\\.schematic1(sch_1):ins40991@templates.\\inductor.normal\\(chips):\\1\\",
			"Logical" : "N409391",
			"Physical" : null
		},
		{
			"Name" : "L3.2",
			"C_PATH" : "@\\nrd52840 circuit\\.schematic1(sch_1):ins40991@templates.\\inductor.normal\\(chips):\\2\\",
			"Logical" : "N17894",
			"Physical" : null
		}
	]
}
